jl_scripts/__init__.py
jl_scripts/app.py
jl_scripts/factorial.py
jl_scripts/factorial_test.py
jl_scripts-0.1.2.dist-info/METADATA
jl_scripts-0.1.2.dist-info/WHEEL
jl_scripts-0.1.2.dist-info/RECORD
