Metadata-Version: 2.1
Name: jl_scripts
Version: 0.1.2
Summary: 
Author: Julie Nguyen
Author-email: tun50867@temple.edu
Requires-Python: >=3.10.14,<4.0.0
Classifier: Programming Language :: Python :: 3
Classifier: Programming Language :: Python :: 3.11
Classifier: Programming Language :: Python :: 3.12
Requires-Dist: streamlit (>=1.32.2,<2.0.0)
